auto_nico/__init__.py
auto_nico/android/__init__.py
auto_nico/android/adb_utils.py
auto_nico/android/nico_android.py
auto_nico/android/nico_android_element.py
auto_nico/android/nico_image.py
auto_nico/android/package/__init__.py
auto_nico/android/package/dump_hierarchy_androidTest_v1.4.apk
auto_nico/android/package/dump_hierarchy_v1.4.apk
auto_nico/android/tools/__init__.py
auto_nico/android/tools/format_converter.py
auto_nico/common/__init__.py
auto_nico/common/common_utils.py
auto_nico/common/error.py
auto_nico/common/kmeans_run.py
auto_nico/common/logger_config.py
auto_nico/common/nico_basic.py
auto_nico/common/nico_basic_element.py
auto_nico/common/runtime_cache.py
auto_nico/common/send_request.py
auto_nico/console_scripts/__init__.py
auto_nico/console_scripts/dump_ui.py
auto_nico/console_scripts/screenshot.py
auto_nico/console_scripts/uninstall_apk.py
auto_nico/console_scripts/inspector_web/__init__.py
auto_nico/console_scripts/inspector_web/nico_inspector.py
auto_nico/console_scripts/inspector_web/pyscrcpy/__init__.py
auto_nico/console_scripts/inspector_web/pyscrcpy/const.py
auto_nico/console_scripts/inspector_web/pyscrcpy/control.py
auto_nico/console_scripts/inspector_web/pyscrcpy/core.py
auto_nico/console_scripts/inspector_web/pyscrcpy/etsdt.py
auto_nico/console_scripts/inspector_web/pyscrcpy/test.py
auto_nico/console_scripts/inspector_web/static/button_script.js
auto_nico/console_scripts/inspector_web/static/script.js
auto_nico/console_scripts/inspector_web/static/styles.css
auto_nico/console_scripts/inspector_web/templates/__init__.py
auto_nico/console_scripts/inspector_web/templates/xml_template.html
auto_nico/console_scripts/test_/__init__.py
auto_nico/console_scripts/test_/app.py
auto_nico/console_scripts/test_/nico_utils.py
auto_nico/console_scripts/test_/scrcpy_utils.py
auto_nico/console_scripts/test_/pyscrcpy/__init__.py
auto_nico/console_scripts/test_/pyscrcpy/const.py
auto_nico/console_scripts/test_/pyscrcpy/control.py
autonico-1.3.16.dist-info/METADATA
autonico-1.3.16.dist-info/WHEEL
autonico-1.3.16.dist-info/entry_points.txt
autonico-1.3.16.dist-info/top_level.txt
autonico-1.3.16.dist-info/RECORD
