Metadata-Version: 2.4
Name: AutoNico
Version: 1.3.16
Summary: Provide Basic Interface to conrol Mobile UI.
Home-page: https://github.com/letmeNo1/nico
Author: Hank Huanng
Author-email: hanhuang@jabra.com
Classifier: Programming Language :: Python :: 3
Classifier: License :: OSI Approved :: MIT License
Classifier: Operating System :: OS Independent
Requires-Python: >=3.6
Requires-Dist: flask==3.0.3
Requires-Dist: lxml==5.1.0
Requires-Dist: numpy>=1.24.4
Requires-Dist: opencv-python==4.9.0.80
Requires-Dist: loguru==0.7.2
Requires-Dist: py-ios==0.1.3
Dynamic: author
Dynamic: author-email
Dynamic: classifier
Dynamic: description
Dynamic: description-content-type
Dynamic: home-page
Dynamic: requires-dist
Dynamic: requires-python
Dynamic: summary
